{"page": 47, "w": 5493, "h": 4250, "hits": [{"text": "充电系统", "conf": 0.9997994303703308, "box": {"x": 679, "y": 185, "w": 364, "h": 98}}, {"text": "12-1", "conf": 0.9985754489898682, "box": {"x": 376, "y": 201, "w": 170, "h": 73}}, {"text": "大电流蓄电池", "conf": 0.9991321563720703, "box": {"x": 954, "y": 1201, "w": 259, "h": 41}}, {"text": "接线盒 (BJB)", "conf": 0.9588302969932556, "box": {"x": 950, "y": 1246, "w": 247, "h": 50}}, {"text": "11-1", "conf": 0.9997631907463074, "box": {"x": 951, "y": 1299, "w": 81, "h": 41}}, {"text": "池盒", "conf": 0.9999186396598816, "box": {"x": 2205, "y": 431, "w": 48, "h": 96}}, {"text": "电线", "conf": 0.9999465942382812, "box": {"x": 2162, "y": 430, "w": 51, "h": 96}}, {"text": "3", "conf": 0.6354734301567078, "box": {"x": 2162, "y": 529, "w": 58, "h": 45}}, {"text": "4", "conf": 0.9996724128723145, "box": {"x": 2166, "y": 573, "w": 40, "h": 41}}, {"text": "蓄接", "conf": 0.9894357919692993, "box": {"x": 2125, "y": 432, "w": 42, "h": 96}}, {"text": "E", "conf": 0.9952754974365234, "box": {"x": 2131, "y": 530, "w": 36, "h": 41}}, {"text": "1", "conf": 0.8224825263023376, "box": {"x": 2137, "y": 581, "w": 23, "h": 26}}, {"text": "RNG2", "conf": 0.9993525147438049, "box": {"x": 1922, "y": 1076, "w": 121, "h": 46}}, {"text": "RD", "conf": 0.9990127086639404, "box": {"x": 1913, "y": 1300, "w": 44, "h": 64}}, {"text": "30-BB10A", "conf": 0.9848393201828003, "box": {"x": 1830, "y": 1173, "w": 33, "h": 185}}, {"text": "C101", "conf": 0.9998302459716797, "box": {"x": 1668, "y": 1073, "w": 105, "h": 50}}, {"text": "RD", "conf": 0.9991416931152344, "box": {"x": 1664, "y": 1300, "w": 43, "h": 64}}, {"text": "PD01A", "conf": 0.9980870485305786, "box": {"x": 1576, "y": 1228, "w": 39, "h": 133}}, {"text": "EMS", "conf": 0.9979895949363708, "box": {"x": 2965, "y": 692, "w": 96, "h": 40}}, {"text": "光雨量传感器", "conf": 0.9996539950370789, "box": {"x": 3508, "y": 692, "w": 246, "h": 38}}, {"text": "26-1", "conf": 0.9999356269836426, "box": {"x": 2973, "y": 742, "w": 87, "h": 40}}, {"text": "LIN", "conf": 0.9967982769012451, "box": {"x": 2757, "y": 943, "w": 71, "h": 38}}, {"text": "LIN BUS2", "conf": 0.9898498058319092, "box": {"x": 3227, "y": 945, "w": 185, "h": 34}}, {"text": "82", "conf": 0.9999042749404907, "box": {"x": 2709, "y": 1081, "w": 50, "h": 38}}, {"text": "C1104b", "conf": 0.9997841715812683, "box": {"x": 2818, "y": 1081, "w": 145, "h": 39}}, {"text": "3", "conf": 0.9964134097099304, "box": {"x": 3273, "y": 1089, "w": 17, "h": 22}}, {"text": "C910", "conf": 0.9987669587135315, "box": {"x": 3358, "y": 1080, "w": 99, "h": 40}}, {"text": "BCC20B", "conf": 0.9988393783569336, "box": {"x": 3259, "y": 1238, "w": 46, "h": 161}}, {"text": "BU-RD", "conf": 0.9991146326065063, "box": {"x": 3345, "y": 1271, "w": 42, "h": 128}}, {"text": "江铃福", "conf": 0.9996688961982727, "box": {"x": 4810, "y": 190, "w": 281, "h": 73}}, {"text": "池盒", "conf": 0.9996916055679321, "box": {"x": 4781, "y": 432, "w": 49, "h": 95}}, {"text": "电线", "conf": 0.9972047805786133, "box": {"x": 4738, "y": 432, "w": 53, "h": 95}}, {"text": "4", "conf": 0.9994319081306458, "box": {"x": 4745, "y": 573, "w": 43, "h": 42}}, {"text": "由接", "conf": 0.722934901714325, "box": {"x": 4706, "y": 463, "w": 38, "h": 64}}, {"text": "S", "conf": 0.9387941360473633, "box": {"x": 4709, "y": 516, "w": 36, "h": 60}}, {"text": "4", "conf": 0.9993178844451904, "box": {"x": 4548, "y": 866, "w": 32, "h": 35}}, {"text": "5", "conf": 0.9978525638580322, "box": {"x": 4543, "y": 773, "w": 26, "h": 38}}, {"text": "6", "conf": 0.9990612864494324, "box": {"x": 4525, "y": 775, "w": 24, "h": 35}}, {"text": "A", "conf": 0.9808173179626465, "box": {"x": 4522, "y": 807, "w": 30, "h": 50}}, {"text": "3", "conf": 0.947302520275116, "box": {"x": 4520, "y": 861, "w": 23, "h": 38}}, {"text": "F5", "conf": 0.998733639717102, "box": {"x": 4499, "y": 773, "w": 24, "h": 88}}, {"text": "常电源", "conf": 0.9999321103096008, "box": {"x": 4375, "y": 374, "w": 131, "h": 53}}, {"text": "BCM", "conf": 0.9978426098823547, "box": {"x": 4152, "y": 688, "w": 102, "h": 48}}, {"text": "C2102c", "conf": 0.9306342005729675, "box": {"x": 3994, "y": 1071, "w": 166, "h": 57}}, {"text": "LIN BUS2", "conf": 0.9980616569519043, "box": {"x": 3878, "y": 939, "w": 195, "h": 48}}, {"text": "2", "conf": 0.9979435801506042, "box": {"x": 3896, "y": 1080, "w": 57, "h": 41}}, {"text": "令福顺", "conf": 0.9534764885902405, "box": {"x": 4929, "y": 185, "w": 191, "h": 84}}, {"text": "接线盒 (BJB)", "conf": 0.9733515977859497, "box": {"x": 950, "y": 1246, "w": 247, "h": 51}}, {"text": "11-1", "conf": 0.9998221397399902, "box": {"x": 949, "y": 1297, "w": 83, "h": 45}}, {"text": "C305", "conf": 0.9993618130683899, "box": {"x": 791, "y": 1473, "w": 101, "h": 39}}, {"text": "F1  350A", "conf": 0.8800497055053711, "box": {"x": 1170, "y": 1469, "w": 180, "h": 42}}, {"text": "SDC04A", "conf": 0.9973601698875427, "box": {"x": 510, "y": 2063, "w": 48, "h": 168}}, {"text": "R", "conf": 0.9003764986991882, "box": {"x": 602, "y": 2167, "w": 43, "h": 64}}, {"text": "C101", "conf": 0.9996885061264038, "box": {"x": 2507, "y": 2573, "w": 109, "h": 43}}, {"text": "RD", "conf": 0.9982695579528809, "box": {"x": 2509, "y": 2412, "w": 39, "h": 65}}, {"text": "SPF01A", "conf": 0.9933314323425293, "box": {"x": 2420, "y": 2317, "w": 38, "h": 156}}, {"text": "C1035a", "conf": 0.9996383190155029, "box": {"x": 1925, "y": 2573, "w": 163, "h": 50}}, {"text": "RD", "conf": 0.9991518259048462, "box": {"x": 1914, "y": 1299, "w": 43, "h": 65}}, {"text": "30-BB", "conf": 0.9901869893074036, "box": {"x": 1830, "y": 1234, "w": 34, "h": 126}}, {"text": "RD", "conf": 0.9991518259048462, "box": {"x": 1664, "y": 1299, "w": 43, "h": 65}}, {"text": "C301a", "conf": 0.9988483190536499, "box": {"x": 1503, "y": 1466, "w": 132, "h": 52}}, {"text": "PD01A", "conf": 0.9979082345962524, "box": {"x": 1576, "y": 1233, "w": 41, "h": 128}}, {"text": "350A", "conf": 0.9409471154212952, "box": {"x": 1267, "y": 1465, "w": 88, "h": 49}}, {"text": "3", "conf": 0.9987276196479797, "box": {"x": 1252, "y": 1471, "w": 28, "h": 37}}, {"text": "C99-A", "conf": 0.9996975660324097, "box": {"x": 3342, "y": 1648, "w": 133, "h": 55}}, {"text": "C39-A", "conf": 0.99933260679245, "box": {"x": 3347, "y": 2045, "w": 124, "h": 45}}, {"text": "BU-RD", "conf": 0.9994928240776062, "box": {"x": 3346, "y": 1271, "w": 39, "h": 130}}, {"text": "OG", "conf": 0.9982740879058838, "box": {"x": 3343, "y": 1878, "w": 44, "h": 69}}, {"text": "OG", "conf": 0.998073399066925, "box": {"x": 3343, "y": 2215, "w": 44, "h": 68}}, {"text": "BCC20B", "conf": 0.9935612678527832, "box": {"x": 3264, "y": 1241, "w": 35, "h": 159}}, {"text": "BCC20BA", "conf": 0.9952078461647034, "box": {"x": 3264, "y": 1755, "w": 35, "h": 189}}, {"text": "BCC20B", "conf": 0.9943487048149109, "box": {"x": 3265, "y": 2122, "w": 35, "h": 159}}, {"text": "3", "conf": 0.9915556311607361, "box": {"x": 3270, "y": 1661, "w": 19, "h": 28}}, {"text": "5", "conf": 0.990791916847229, "box": {"x": 3246, "y": 2050, "w": 24, "h": 35}}, {"text": "C11-A", "conf": 0.9998115301132202, "box": {"x": 2811, "y": 2044, "w": 124, "h": 46}}, {"text": "C1232", "conf": 0.999488353729248, "box": {"x": 2790, "y": 2571, "w": 153, "h": 48}}, {"text": "BU-GN", "conf": 0.9996541738510132, "box": {"x": 2808, "y": 1812, "w": 39, "h": 133}}, {"text": "BU-GN", "conf": 0.9997726678848267, "box": {"x": 2806, "y": 2337, "w": 42, "h": 137}}, {"text": "ECK82A", "conf": 0.999014139175415, "box": {"x": 2723, "y": 1784, "w": 40, "h": 161}}, {"text": "ECK82B", "conf": 0.9989448189735413, "box": {"x": 2725, "y": 2316, "w": 37, "h": 157}}, {"text": "S", "conf": 0.7649338245391846, "box": {"x": 2732, "y": 2056, "w": 16, "h": 25}}, {"text": "C1014a", "conf": 0.999270498752594, "box": {"x": 2511, "y": 2571, "w": 158, "h": 47}}, {"text": "RD", "conf": 0.9986113905906677, "box": {"x": 2506, "y": 2412, "w": 44, "h": 65}}, {"text": "BCC20A", "conf": 0.9995870590209961, "box": {"x": 3912, "y": 1782, "w": 46, "h": 166}}, {"text": "PF65A", "conf": 0.9996929168701172, "box": {"x": 4393, "y": 1814, "w": 46, "h": 132}}, {"text": "OG", "conf": 0.9977664947509766, "box": {"x": 3995, "y": 1876, "w": 47, "h": 72}}, {"text": "WH", "conf": 0.9993599057197571, "box": {"x": 4483, "y": 1871, "w": 45, "h": 76}}, {"text": "BCC20", "conf": 0.999147891998291, "box": {"x": 4008, "y": 2326, "w": 111, "h": 39}}, {"text": "BCC20C", "conf": 0.9992432594299316, "box": {"x": 3913, "y": 2364, "w": 45, "h": 173}}, {"text": "G", "conf": 0.9957501888275146, "box": {"x": 3998, "y": 2463, "w": 42, "h": 41}}, {"text": "O", "conf": 0.6017727255821228, "box": {"x": 4000, "y": 2493, "w": 38, "h": 37}}, {"text": "2", "conf": 0.9998633861541748, "box": {"x": 4398, "y": 2548, "w": 24, "h": 31}}, {"text": "C2032", "conf": 0.9996310472488403, "box": {"x": 4505, "y": 2546, "w": 123, "h": 36}}, {"text": "7", "conf": 0.9570877552032471, "box": {"x": 3923, "y": 2551, "w": 18, "h": 19}}, {"text": "蓄电池", "conf": 0.998683750629425, "box": {"x": 648, "y": 2939, "w": 132, "h": 54}}, {"text": "C304a", "conf": 0.9989877939224243, "box": {"x": 609, "y": 2834, "w": 131, "h": 50}}, {"text": "5.", "conf": 0.9410251379013062, "box": {"x": 715, "y": 3533, "w": 27, "h": 43}}, {"text": "5", "conf": 0.9939953684806824, "box": {"x": 710, "y": 3579, "w": 30, "h": 38}}, {"text": "2", "conf": 0.9993051290512085, "box": {"x": 692, "y": 3533, "w": 30, "h": 38}}, {"text": "1", "conf": 0.9921423196792603, "box": {"x": 689, "y": 3585, "w": 27, "h": 27}}, {"text": "3", "conf": 0.9976392984390259, "box": {"x": 666, "y": 2998, "w": 37, "h": 31}}, {"text": "100", "conf": 0.6327113509178162, "box": {"x": 632, "y": 3575, "w": 65, "h": 44}}, {"text": "BK", "conf": 0.9998630285263062, "box": {"x": 600, "y": 3410, "w": 44, "h": 62}}, {"text": "州王", "conf": 0.896084189414978, "box": {"x": 541, "y": 2950, "w": 75, "h": 219}}, {"text": "GD25A", "conf": 0.9979223012924194, "box": {"x": 515, "y": 3280, "w": 38, "h": 144}}, {"text": "A", "conf": 0.9983624815940857, "box": {"x": 521, "y": 3427, "w": 28, "h": 37}}, {"text": "C1014", "conf": 0.9912985563278198, "box": {"x": 2495, "y": 2572, "w": 131, "h": 43}}, {"text": "B+", "conf": 0.9977571964263916, "box": {"x": 2494, "y": 2666, "w": 72, "h": 43}}, {"text": "起动机", "conf": 0.9990904927253723, "box": {"x": 2236, "y": 2635, "w": 130, "h": 50}}, {"text": "C1035a", "conf": 0.9994553923606873, "box": {"x": 1927, "y": 2571, "w": 161, "h": 53}}, {"text": "C1035d", "conf": 0.999626636505127, "box": {"x": 1926, "y": 3098, "w": 149, "h": 43}}, {"text": "GD214", "conf": 0.9997897148132324, "box": {"x": 1944, "y": 3576, "w": 139, "h": 42}}, {"text": "BK", "conf": 0.9998478889465332, "box": {"x": 1914, "y": 3342, "w": 45, "h": 62}}, {"text": "31-BA11", "conf": 0.9975093007087708, "box": {"x": 1830, "y": 3244, "w": 34, "h": 156}}, {"text": "TR", "conf": 0.9982802867889404, "box": {"x": 1669, "y": 3009, "w": 69, "h": 42}}, {"text": "S", "conf": 0.9550632238388062, "box": {"x": 1644, "y": 3012, "w": 28, "h": 39}}, {"text": "发电机", "conf": 0.9999316334724426, "box": {"x": 2953, "y": 2638, "w": 129, "h": 51}}, {"text": "C1232", "conf": 0.9995899200439453, "box": {"x": 2770, "y": 2572, "w": 171, "h": 46}}, {"text": "GD18", "conf": 0.9997542500495911, "box": {"x": 2800, "y": 3572, "w": 120, "h": 48}}, {"text": "LIN", "conf": 0.99664705991745, "box": {"x": 2802, "y": 2664, "w": 78, "h": 46}}, {"text": "CG", "conf": 0.9998114109039307, "box": {"x": 2763, "y": 3007, "w": 79, "h": 42}}, {"text": "C", "conf": 0.5197587013244629, "box": {"x": 2777, "y": 3099, "w": 55, "h": 39}}, {"text": "BK", "conf": 0.9998009204864502, "box": {"x": 2773, "y": 3341, "w": 45, "h": 65}}, {"text": "GD18A", "conf": 0.9974803924560547, "box": {"x": 2691, "y": 3213, "w": 35, "h": 145}}, {"text": "A", "conf": 0.9982275366783142, "box": {"x": 2696, "y": 3352, "w": 27, "h": 46}}, {"text": "C1014a", "conf": 0.9995400309562683, "box": {"x": 2510, "y": 2571, "w": 159, "h": 47}}, {"text": "B+", "conf": 0.9988635778427124, "box": {"x": 2497, "y": 2665, "w": 70, "h": 44}}, {"text": "G", "conf": 0.9969040751457214, "box": {"x": 3999, "y": 2466, "w": 38, "h": 36}}, {"text": "B", "conf": 0.9989830851554871, "box": {"x": 3918, "y": 2500, "w": 34, "h": 30}}, {"text": "O", "conf": 0.6681627035140991, "box": {"x": 4002, "y": 2493, "w": 33, "h": 34}}, {"text": "2", "conf": 0.9934858679771423, "box": {"x": 4396, "y": 2548, "w": 26, "h": 29}}, {"text": "C2032", "conf": 0.9994943737983704, "box": {"x": 4506, "y": 2546, "w": 122, "h": 38}}, {"text": "蓄电池", "conf": 0.998155415058136, "box": {"x": 4601, "y": 2640, "w": 125, "h": 43}}, {"text": "LIN", "conf": 0.9974185824394226, "box": {"x": 3947, "y": 2683, "w": 69, "h": 43}}, {"text": "电源", "conf": 0.9999510645866394, "box": {"x": 4427, "y": 2678, "w": 84, "h": 49}}, {"text": "传感器", "conf": 0.9995670318603516, "box": {"x": 4598, "y": 2694, "w": 128, "h": 46}}]}