{"page": 20, "w": 5493, "h": 4250, "hits": [{"text": "江铃福顺", "conf": 0.9993220567703247, "box": {"x": 373, "y": 191, "w": 301, "h": 72}}, {"text": "注", "conf": 0.9993645548820496, "box": {"x": 371, "y": 372, "w": 63, "h": 63}}, {"text": "符号", "conf": 0.9959486722946167, "box": {"x": 4622, "y": 180, "w": 190, "h": 111}}, {"text": "4-6", "conf": 0.9714379906654358, "box": {"x": 4982, "y": 196, "w": 113, "h": 83}}, {"text": "4-6", "conf": 0.9999369978904724, "box": {"x": 4983, "y": 196, "w": 139, "h": 85}}]}